anibridge/list/__init__.py
anibridge/list/base.py
anibridge/list/registry.py
anibridge_list_base-0.1.1.dist-info/WHEEL
anibridge_list_base-0.1.1.dist-info/METADATA
anibridge_list_base-0.1.1.dist-info/RECORD
