Metadata-Version: 2.3
Name: anibridge-list-base
Version: 0.1.1
Summary: List provider base classes for the AniBridge project.
Author: Elias Benbourenane
Author-email: Elias Benbourenane <eliasbenbourenane@gmail.com>
License: MIT
Classifier: Programming Language :: Python :: 3
Classifier: Programming Language :: Python :: 3.14
Classifier: License :: OSI Approved :: MIT License
Classifier: Operating System :: OS Independent
Maintainer: Elias Benbourenane
Maintainer-email: Elias Benbourenane <eliasbenbourenane@gmail.com>
Requires-Python: >=3.14
